README.txt
setup.py
Pyjamas_Desktop.egg-info/PKG-INFO
Pyjamas_Desktop.egg-info/SOURCES.txt
Pyjamas_Desktop.egg-info/dependency_links.txt
Pyjamas_Desktop.egg-info/top_level.txt
Pyjamas_Desktop.egg-info/zip-safe
bin/pyjd.py
pyjamas/AutoComplete.py
pyjamas/BoundMethod.py
pyjamas/Canvas.py
pyjamas/Cookies.py
pyjamas/CountryListBox.py
pyjamas/DOM.py
pyjamas/DeferredCommand.py
pyjamas/EventDelegate.py
pyjamas/HTTPRequest.py
pyjamas/History.py
pyjamas/JSONParser.py
pyjamas/JSONService.py
pyjamas/Location.py
pyjamas/PyJSONService.py
pyjamas/RichTextEditor.py
pyjamas/TemplatePanel.py
pyjamas/Timer.py
pyjamas/Tooltip.py
pyjamas/Window.py
pyjamas/__init__.py
pyjamas/__pyjamas__.py
pyjamas/pygwt.py
pyjamas/pyjslib.py
pyjamas/ui.py