Metadata-Version: 1.0
Name: Pyjamas-Desktop
Version: 0.01
Summary: Pyjamas Widget API for Desktop applications, in Python
Home-page: http://pyamf.org
Author: The Pyjamas Desktop Project
Author-email: lkcl@lkcl.net
License: Apache Software License
Platform: any
Classifier: Development Status :: 3 - Alpha
Classifier: Natural Language :: English
Classifier: Intended Audience :: Developers
Classifier: License :: OSI Approved :: Apache Software License
Classifier: Operating System :: OS Independent
Classifier: Programming Language :: Python
